docly/__init__.py
docly/cli/__init__.py
docly/cli/args.py
docly/cli/docly_clean.py
docly/cli/docly_gen.py
docly/cli/docly_restore.py
docly/cli/setup_env.py
docly/config/__init__.py
docly/ioutils/__init__.py
docly/ioutils/apply_diff.py
docly/ioutils/console_printer.py
docly/ioutils/convert_ipynb.py
docly/ioutils/table_printer.py
docly/logic/__init__.py
docly/logic/example.py
docly/logic/input_features.py
docly/logic/logic_main.py
docly/logic/model.py
docly/logic/model_new.py
docly/parser/__init__.py
docly/parser/parser.py
docly/tokenizers/__init__.py
docly-0.2.1.dist-info/LICENSE
docly-0.2.1.dist-info/METADATA
docly-0.2.1.dist-info/WHEEL
docly-0.2.1.dist-info/entry_points.txt
docly-0.2.1.dist-info/top_level.txt
docly-0.2.1.dist-info/RECORD
