Metadata-Version: 2.1
Name: docly
Version: 0.2.1
Summary: Generate docstrings for your python functions. Automatically!
Home-page: https://github.com/autosoft-dev/docly
Author: CodistAI
Author-email: shubhadeep@codist-ai.com
License: MIT
Platform: UNKNOWN
Classifier: License :: OSI Approved :: MIT License
Classifier: Programming Language :: Python :: 3
Classifier: Programming Language :: Python :: 3.6
Requires-Dist: tqdm
Requires-Dist: requests
Requires-Dist: torch
Requires-Dist: pyfiglet
Requires-Dist: rich
Requires-Dist: dpu-utils
Requires-Dist: numpy
Requires-Dist: nltk
Requires-Dist: transformers (==2.5.0)
Requires-Dist: tree-hugger
Requires-Dist: halo
Requires-Dist: invoke
Provides-Extra: jupyter
Requires-Dist: jupytext ; extra == 'jupyter'
